{
	"configurations" : 
	[
		{
			"directories" : 
			[
				{
					"build" : ".",
					"jsonFile" : "directory-.-Debug-f5ebdc15457944623624.json",
					"minimumCMakeVersion" : 
					{
						"string" : "3.10"
					},
					"projectIndex" : 0,
					"source" : ".",
					"targetIndexes" : 
					[
						0
					]
				}
			],
			"name" : "Debug",
			"projects" : 
			[
				{
					"directoryIndexes" : 
					[
						0
					],
					"name" : "ReserFISI",
					"targetIndexes" : 
					[
						0
					]
				}
			],
			"targets" : 
			[
				{
					"directoryIndex" : 0,
					"id" : "ReserFISI::@6890427a1f51a3e7e1df",
					"jsonFile" : "target-ReserFISI-Debug-8440c7fd1a1ffa39815c.json",
					"name" : "ReserFISI",
					"projectIndex" : 0
				}
			]
		}
	],
	"kind" : "codemodel",
	"paths" : 
	{
		"build" : "/home/sebastianrojas/Escritorio/ReserFISI/build",
		"source" : "/home/sebastianrojas/Escritorio/ReserFISI"
	},
	"version" : 
	{
		"major" : 2,
		"minor" : 6
	}
}
